escape/__init__.py
escape/ansi_styles.py
escape/core.py
escape-1.0.dist-info/DESCRIPTION.rst
escape-1.0.dist-info/METADATA
escape-1.0.dist-info/RECORD
escape-1.0.dist-info/WHEEL
escape-1.0.dist-info/metadata.json
escape-1.0.dist-info/top_level.txt
